milad/__init__.py
milad/analytic.py
milad/atomic.py
milad/base_moments.py
milad/exceptions.py
milad/fingerprinting.py
milad/functions.py
milad/generate.py
milad/geometric.py
milad/mathutil.py
milad/plot.py
milad/plotlytools.py
milad/polynomials.py
milad/provides.py
milad/rdkittools.py
milad/reconstruct.py
milad/sph.py
milad/testing.py
milad/transform.py
milad/utils.py
milad/version.py
milad/zernike.py
milad/dat/__init__.py
milad/dat/fingerprint_set.py
milad/descriptors/__init__.py
milad/descriptors/_dscribe.py
milad/descriptors/amp_adapter.py
milad/descriptors/interfaces.py
milad/descriptors/invariants_generation.py
milad/invariants/__init__.py
milad/invariants/interfaces.py
milad/invariants/invertible_invariants.py
milad/invariants/moment_invariants.py
milad/invariants/powerspectrum.py
milad/invariants/res/cmfs7indep_0.orig.txt
milad/invariants/res/cmfs7indep_0.txt
milad/invariants/res/cmfs7indep_0.txt.bak
milad/invariants/res/cmfs7indep_0_first_order.txt
milad/invariants/res/milad_rot3dinvs8indep.txt
milad/invariants/res/rot3dinvs8indep.txt
milad/invariants/res/rot3dinvs8mat.txt
milad/models/__init__.py
milad/models/neuralnetwork.py
milad/models/utils.py
milad/optimisers/__init__.py
milad/optimisers/least_squares.py
milad/optimisers/moments_optimiser.py
milad/optimisers/root.py
milad/optimisers/structure_optimiser.py
milad/optimisers/utils.py
milad/play/__init__.py
milad/play/asetools.py
milad/play/distances.py
milad/play/envs.py
milad/play/fingerprints.py
milad-0.3.1.dist-info/METADATA
milad-0.3.1.dist-info/WHEEL
milad-0.3.1.dist-info/dependency_links.txt
milad-0.3.1.dist-info/entry_points.txt
milad-0.3.1.dist-info/top_level.txt
milad-0.3.1.dist-info/RECORD
