Metadata-Version: 2.1
Name: milad
Version: 0.3.1
Summary: Moment Invariants Local Atomic Descriptor
Home-page: https://github.com/muhrin/milad.git
Author: Martin Uhrin
Author-email: martin.uhrin.10@ucl.ac.uk
License: GPLv3
Keywords: machine learning,atomic descriptor,moment invariants
Platform: UNKNOWN
Classifier: License :: OSI Approved :: GNU General Public License v3 (GPLv3)
Classifier: Programming Language :: Python :: 3.7
Classifier: Programming Language :: Python :: 3.8
Classifier: Programming Language :: Python :: 3.9
Classifier: Programming Language :: Python :: 3.10
Requires-Python: >=3.6
Requires-Dist: dscribe
Requires-Dist: matplotlib
Requires-Dist: miniball
Requires-Dist: numba
Requires-Dist: numpy
Requires-Dist: rmsd
Requires-Dist: torch
Requires-Dist: scipy
Requires-Dist: sympy
Requires-Dist: scikit-learn
Requires-Dist: scikit-image
Requires-Dist: typing-extensions
Provides-Extra: dev
Requires-Dist: ipython ; extra == 'dev'
Requires-Dist: pip ; extra == 'dev'
Requires-Dist: pytest (~=7.2) ; extra == 'dev'
Requires-Dist: pytest-cov ; extra == 'dev'
Requires-Dist: pre-commit (~=2.2) ; extra == 'dev'
Requires-Dist: twine ; extra == 'dev'
